{
  "events": [
    {
      "name": "Join YoSinTV Telegram Channel",
      "link": "https://t.me/yosintvlive"
    },

{
  "name": " Dortmund vs Leverkusen",
  "links": [
    "https://yosintv2.github.io/ads/foot.html?url=https://ytvlive.pages.dev/zhi?m=5fa1b870884166e3ef9fb2308c9660c2 ",
    "http://yosintv-api.pages.dev/api/ads",
    "https://yosintv2.github.io/ads/foot.html?url=https://ytvlive.pages.dev/zhi?m=5fa1b870884166e3ef9fb2308c9660c2 ",
    "https://yosintv2.github.io/ads/foot.html?url=https://ytvlive.pages.dev/ak?m=511367",
    "https://yosintv-api.pages.dev/api/ads", 
    "https://yosintv2.github.io/ads/foot.html?url=https://ytvlive.pages.dev/ak?m=285067" 
  ]
} 
,
{
  "name": "💻 Dortmund vs Leverkusen",
  "links": [
    "http://yosintv-api.pages.dev/api/ads",
    "https://yosintv2.github.io/ads/foot.html?url=https://topembed.pw/channel/DigiSport2[Romania]",
    "https://yosintv2.github.io/ads/foot.html?url=https://topembed.pw/channel/ESPN3[Argentina]",
    "https://yosintv2.github.io/ads/foot.html?url=https://topembed.pw/channel/SkySport2[Germany]",
    "https://yosintv2.github.io/ads/foot.html?url=https://topembed.pw/channel/ex8931355"
  ]
}

  ],
  "styles": {
    "livee": "display: flex; justify-content: center; align-items: center; text-decoration: none; color: inherit; margin: 5px 0; padding: 10px; border: 2px solid #000; border-radius: 5px; cursor: pointer; transition: box-shadow 0.3s ease; background-color: red; color: white;",
    "liveeHover": "box-shadow: 0 4px 8px rgba(0, 0, 0, 0.2);",
    "liveeName": "flex: 2; text-align: center; color: white; font-weight: bold;"
  }
}
