{
  "events": [
    {
      "name": "Join YoSinTV Telegram Channel",
      "link": "https://t.me/yosintvlive"
    },

{
  "name": "📱💻 Juventus vs. Sporting ",
  "links": [
    "https://yosintv2.github.io/ads/foot.html?url=https://ytvlive.pages.dev/admin?mid=ppv-juventus-vs-sporting-cp ",
    "https://yosintv2.pages.dev/ads.html",
    "https://yosintv2.github.io/ads/foot.html?url=https://ytvlive.pages.dev/admin?mid=ppv-juventus-vs-sporting-cp ",
    "https://yosintv2.github.io/ads/foot.html?url=https://ytvlive.pages.dev/ak?m=501412",
    "https://yosintv2.github.io/ads.html", 
    "https://yosintv2.github.io/ads/foot.html?url=https://ytvlive.pages.dev/ak?m=548860" 
  ]
} ,

{
  "name": "💻 Juventus vs Sporting",
  "links": [
    "https://yosintv2.pages.dev/ads.html",
    "https://yosintv2.github.io/ads/foot.html?url=https://topembed.pw/channel/TNTSports4[UK]",
    "https://yosintv2.github.io/ads/foot.html?url=https://topembed.pw/channel/ESPN3[Argentina]",
    "https://yosintv2.github.io/ads/foot.html?url=https://topembed.pw/channel/DAZN2Deutschland[Germany]",
    "https://yosintv2.github.io/ads/foot.html?url=https://topembed.pw/channel/CosmoteSport6[Greece]"
  ]
}

  ],
  "styles": {
    "livee": "display: flex; justify-content: center; align-items: center; text-decoration: none; color: inherit; margin: 5px 0; padding: 10px; border: 2px solid #000; border-radius: 5px; cursor: pointer; transition: box-shadow 0.3s ease; background-color: red; color: white;",
    "liveeHover": "box-shadow: 0 4px 8px rgba(0, 0, 0, 0.2);",
    "liveeName": "flex: 2; text-align: center; color: white; font-weight: bold;"
  }
}
